a_star_2048/__init__.py
a_star_2048/a_star.py
a_star_2048/board.py
a_star_2048-0.1.0.dist-info/LICENSE
a_star_2048-0.1.0.dist-info/METADATA
a_star_2048-0.1.0.dist-info/WHEEL
a_star_2048-0.1.0.dist-info/RECORD
