Metadata-Version: 2.3
Name: a_star_2048
Version: 0.1.0
Summary: Solving 2048 using A star with multiple heuristics
Home-page: https://github.com/Joao-Pedro-P-Holanda/a-star-2048
License: GPLv3
Author: joaopedroph
Author-email: joaopedroph.dev@gmail.com
Requires-Python: >=3.11
Classifier: License :: Other/Proprietary License
Classifier: Programming Language :: Python :: 3
Classifier: Programming Language :: Python :: 3.11
Classifier: Programming Language :: Python :: 3.12
Classifier: Programming Language :: Python :: 3.13
